server.py
mseep_aws_geoplaces_mcp_server-0.1.1.dist-info/licenses/LICENSE
mseep_aws_geoplaces_mcp_server-0.1.1.dist-info/METADATA
mseep_aws_geoplaces_mcp_server-0.1.1.dist-info/WHEEL
mseep_aws_geoplaces_mcp_server-0.1.1.dist-info/top_level.txt
mseep_aws_geoplaces_mcp_server-0.1.1.dist-info/RECORD
