Metadata-Version: 2.4
Name: mseep-aws-geoplaces-mcp-server
Version: 0.1.1
Summary: Add your description here
Author-email: mseep <support@skydeck.ai>
Requires-Python: >=3.13
License-File: LICENSE
Requires-Dist: boto3>=1.38.10
Requires-Dist: mcp[cli]>=1.7.1
Requires-Dist: python-dotenv>=1.1.0
Dynamic: license-file
